Workbook

Sheet Quarterly IS
A1: Tesla, Inc. — Quarterly Income Statement (Synthetic)
A2: Synthetic example — NOT actual Tesla results. USD millions unless noted.
A4: Line item (USD millions) | B4: Q1 2021 | C4: Q2 2021 | D4: Q3 2021 | E4: Q4 2021 | F4: Q1 2022 | G4: Q2 2022 | H4: Q3 2022 | I4: Q4 2022 | J4: Q1 2023 | K4: Q2 2023 | L4: Q3 2023 | M4: Q4 2023 | N4: Q1 2024 | O4: Q2 2024 | P4: Q3 2024 | Q4: Q4 2024 | R4: Q1 2025 | S4: Q2 2025 | T4: Q3 2025 | U4: Q4 2025
A5: Automotive revenues | B5: 7500 | C5: 8600 | D5: 9800 | E5: 11200 | F5: 12300 | G5: 13800 | H5: 15200 | I5: 16800 | J5: 18500 | K5: 19500 | L5: 20400 | M5: 21000 | N5: 20000 | O5: 21500 | P5: 22500 | Q5: 23500 | R5: 24500 | S5: 26000 | T5: 27500 | U5: 28500
A6: Energy generation & storage revenues | B6: 1500 | C6: 1600 | D6: 1750 | E6: 1900 | F6: 2100 | G6: 2250 | H6: 2400 | I6: 2600 | J6: 2900 | K6: 3100 | L6: 3350 | M6: 3600 | N6: 3900 | O6: 4100 | P6: 4300 | Q6: 4600 | R6: 4900 | S6: 5300 | T6: 5700 | U6: 6100
A7: Services and other revenues | B7: 1200 | C7: 1300 | D7: 1450 | E7: 1600 | F7: 1750 | G7: 1900 | H7: 2050 | I7: 2250 | J7: 2450 | K7: 2600 | L7: 2750 | M7: 2950 | N7: 3050 | O7: 3180 | P7: 3300 | Q7: 3450 | R7: 3600 | S7: 3750 | T7: 3900 | U7: 4100
A8: Total revenues | B8: =SUM(B5:B7) -> 10200 | C8: =SUM(C5:C7) -> 11500 | D8: =SUM(D5:D7) -> 13000 | E8: =SUM(E5:E7) -> 14700 | F8: =SUM(F5:F7) -> 16150 | G8: =SUM(G5:G7) -> 17950 | H8: =SUM(H5:H7) -> 19650 | I8: =SUM(I5:I7) -> 21650 | ... U8: =SUM(U5:U7) -> 38700
A9: Cost of revenues | B9: 7650 | C9: 8700 | D9: 9850 | E9: 11200 | F9: 11950 | G9: 13150 | H9: 14250 | I9: 15450 | J9: 17650 | K9: 18250 | L9: 19000 | M9: 19750 | N9: 19600 | O9: 21300 | P9: 22100 | Q9: 23100 | R9: 24200 | S9: 25400 | T9: 26500 | U9: 27500
A10: Gross profit | B10: =B8-B9 -> 2550 | C10: =C8-C9 -> 2800 | D10: =D8-D9 -> 3150 | E10: =E8-E9 -> 3500 | F10: =F8-F9 -> 4200 | G10: =G8-G9 -> 4800 | H10: =H8-H9 -> 5400 | I10: =I8-I9 -> 6200 | ... U10: =U8-U9 -> 11200
A11: Gross margin (%) | B11: =B10/B8 -> 0.25 | C11: =C10/C8 -> 0.24347826 | D11: =D10/D8 -> 0.24230769 | E11: =E10/E8 -> 0.23809524 | F11: =F10/F8 -> 0.26006192 | G11: =G10/G8 -> 0.26740947 | H11: =H10/H8 -> 0.27480916 | I11: =I10/I8 -> 0.28637413 | ... U11: =U10/U8 -> 0.28940568
A12: Research & development | B12: 550 | C12: 575 | D12: 600 | E12: 625 | F12: 650 | G12: 675 | H12: 700 | I12: 725 | J12: 750 | K12: 775 | L12: 800 | M12: 825 | N12: 850 | O12: 875 | P12: 900 | Q12: 925 | R12: 950 | S12: 975 | T12: 1000 | U12: 1050
A13: Selling, general & administrative | B13: 450 | C13: 465 | D13: 480 | E13: 500 | F13: 515 | G13: 530 | H13: 550 | I13: 570 | J13: 585 | K13: 600 | L13: 620 | M13: 640 | N13: 650 | O13: 660 | P13: 675 | Q13: 690 | R13: 700 | S13: 715 | T13: 730 | U13: 750
A14: Total operating expenses | B14: =B12+B13 -> 1000 | C14: =C12+C13 -> 1040 | D14: =D12+D13 -> 1080 | E14: =E12+E13 -> 1125 | F14: =F12+F13 -> 1165 | G14: =G12+G13 -> 1205 | H14: =H12+H13 -> 1250 | I14: =I12+I13 -> 1295 | ... U14: =U12+U13 -> 1800
A15: Operating income | B15: =B10-B14 -> 1550 | C15: =C10-C14 -> 1760 | D15: =D10-D14 -> 2070 | E15: =E10-E14 -> 2375 | F15: =F10-F14 -> 3035 | G15: =G10-G14 -> 3595 | H15: =H10-H14 -> 4150 | I15: =I10-I14 -> 4905 | ... U15: =U10-U14 -> 9400
A16: Operating margin (%) | B16: =B15/B8 -> 0.15196078 | C16: =C15/C8 -> 0.15304348 | D16: =D15/D8 -> 0.15923077 | E16: =E15/E8 -> 0.16156463 | F16: =F15/F8 -> 0.1879257 | G16: =G15/G8 -> 0.20027855 | H16: =H15/H8 -> 0.21119593 | I16: =I15/I8 -> 0.22655889 | ... U16: =U15/U8 -> 0.24289406
A17: Interest income | B17: 30 | C17: 35 | D17: 40 | E17: 45 | F17: 50 | G17: 55 | H17: 60 | I17: 65 | J17: 80 | K17: 85 | L17: 90 | M17: 95 | N17: 100 | O17: 105 | P17: 110 | Q17: 115 | R17: 120 | S17: 125 | T17: 130 | U17: 135
A18: Interest expense | B18: 90 | C18: 90 | D18: 95 | E18: 95 | F18: 100 | G18: 100 | H18: 105 | I18: 105 | J18: 110 | K18: 110 | L18: 110 | M18: 110 | N18: 108 | O18: 108 | P18: 106 | Q18: 106 | R18: 104 | S18: 104 | T18: 102 | U18: 102
A19: Other income/(expense), net | B19: 20 | C19: 25 | D19: 15 | E19: 30 | F19: 10 | G19: -15 | H19: 25 | I19: -10 | J19: 5 | K19: 15 | L19: -5 | M19: 10 | N19: 12 | O19: -8 | P19: 18 | Q19: 5 | R19: 10 | S19: 15 | T19: -10 | U19: 20
A20: Pre-tax income | B20: =B15+B17-B18+B19 -> 1510 | C20: =C15+C17-C18+C19 -> 1730 | D20: =D15+D17-D18+D19 -> 2030 | E20: =E15+E17-E18+E19 -> 2355 | F20: =F15+F17-F18+F19 -> 2995 | G20: =G15+G17-G18+G19 -> 3535 | H20: =H15+H17-H18+H19 -> 4130 | I20: =I15+I17-I18+I19 -> 4855 | ... U20: =U15+U17-U18+U19 -> 9453
A21: Provision for income taxes | B21: =ROUND(B20*Assumptions!$B$5,0) -> 302 | C21: =ROUND(C20*Assumptions!$B$5,0) -> 346 | D21: =ROUND(D20*Assumptions!$B$5,0) -> 406 | E21: =ROUND(E20*Assumptions!$B$5,0) -> 471 | F21: =ROUND(F20*Assumptions!$B$5,0) -> 599 | G21: =ROUND(G20*Assumptions!$B$5,0) -> 707 | H21: =ROUND(H20*Assumptions!$B$5,0) -> 826 | I21: =ROUND(I20*Assumptions!$B$5,0) -> 971 | ... U21: =ROUND(U20*Assumptions!$B$5,0) -> 1891
A22: Net income | B22: =B20-B21 -> 1208 | C22: =C20-C21 -> 1384 | D22: =D20-D21 -> 1624 | E22: =E20-E21 -> 1884 | F22: =F20-F21 -> 2396 | G22: =G20-G21 -> 2828 | H22: =H20-H21 -> 3304 | I22: =I20-I21 -> 3884 | ... U22: =U20-U21 -> 7562
A23: Net margin (%) | B23: =B22/B8 -> 0.11843137 | C23: =C22/C8 -> 0.12034783 | D23: =D22/D8 -> 0.12492308 | E23: =E22/E8 -> 0.12816327 | F23: =F22/F8 -> 0.14835913 | G23: =G22/G8 -> 0.15754875 | H23: =H22/H8 -> 0.16814249 | I23: =I22/I8 -> 0.17939954 | ... U23: =U22/U8 -> 0.19540052
A24: Diluted EPS (USD) | B24: =B22/Assumptions!$B$6 -> 0.35014493 | C24: =C22/Assumptions!$B$6 -> 0.40115942 | D24: =D22/Assumptions!$B$6 -> 0.47072464 | E24: =E22/Assumptions!$B$6 -> 0.54608696 | F24: =F22/Assumptions!$B$6 -> 0.69449275 | G24: =G22/Assumptions!$B$6 -> 0.81971014 | H24: =H22/Assumptions!$B$6 -> 0.95768116 | I24: =I22/Assumptions!$B$6 -> 1.1257971 | ... U24: =U22/Assumptions!$B$6 -> 2.1918841

Sheet Annual Summary
A1: Tesla, Inc. — Annual Summary (Synthetic)
A2: Synthetic example — NOT actual Tesla results. USD millions unless noted. Annual figures = sum of the four calendar quarters.
A4: Line item (USD millions) | B4: 2021 | C4: 2022 | D4: 2023 | E4: 2024 | F4: 2025 | G4: CAGR 2021–25
A5: Automotive revenues | B5: =SUM('Quarterly IS'!B5:E5) -> 37100 | C5: =SUM('Quarterly IS'!F5:I5) -> 58100 | D5: =SUM('Quarterly IS'!J5:M5) -> 79400 | E5: =SUM('Quarterly IS'!N5:Q5) -> 87500 | F5: =SUM('Quarterly IS'!R5:U5) -> 106500 | G5: =(F5/B5)^(1/4)-1 -> 0.30164911
A6: Energy generation & storage revenues | B6: =SUM('Quarterly IS'!B6:E6) -> 6750 | C6: =SUM('Quarterly IS'!F6:I6) -> 9350 | D6: =SUM('Quarterly IS'!J6:M6) -> 12950 | E6: =SUM('Quarterly IS'!N6:Q6) -> 16900 | F6: =SUM('Quarterly IS'!R6:U6) -> 22000 | G6: =(F6/B6)^(1/4)-1 -> 0.34363011
A7: Services and other revenues | B7: =SUM('Quarterly IS'!B7:E7) -> 5550 | C7: =SUM('Quarterly IS'!F7:I7) -> 7950 | D7: =SUM('Quarterly IS'!J7:M7) -> 10750 | E7: =SUM('Quarterly IS'!N7:Q7) -> 12980 | F7: =SUM('Quarterly IS'!R7:U7) -> 15350 | G7: =(F7/B7)^(1/4)-1 -> 0.28959651
A8: Total revenues | B8: =SUM(B5:B7) -> 49400 | C8: =SUM(C5:C7) -> 75400 | D8: =SUM(D5:D7) -> 103100 | E8: =SUM(E5:E7) -> 117380 | F8: =SUM(F5:F7) -> 143850 | G8: =(F8/B8)^(1/4)-1 -> 0.30630843
A9: Cost of revenues | B9: =SUM('Quarterly IS'!B9:E9) -> 37400 | C9: =SUM('Quarterly IS'!F9:I9) -> 54800 | D9: =SUM('Quarterly IS'!J9:M9) -> 74650 | E9: =SUM('Quarterly IS'!N9:Q9) -> 86100 | F9: =SUM('Quarterly IS'!R9:U9) -> 103600 | G9: =(F9/B9)^(1/4)-1 -> 0.29009603
A10: Gross profit | B10: =B8-B9 -> 12000 | C10: =C8-C9 -> 20600 | D10: =D8-D9 -> 28450 | E10: =E8-E9 -> 31280 | F10: =F8-F9 -> 40250 | G10: =(F10/B10)^(1/4)-1 -> 0.35330647
A11: Gross margin (%) | B11: =B10/B8 -> 0.24291498 | C11: =C10/C8 -> 0.27320955 | D11: =D10/D8 -> 0.27594568 | E11: =E10/E8 -> 0.26648492 | F11: =F10/F8 -> 0.27980535 | G11: —
A12: Research & development | B12: =SUM('Quarterly IS'!B12:E12) -> 2350 | C12: =SUM('Quarterly IS'!F12:I12) -> 2750 | D12: =SUM('Quarterly IS'!J12:M12) -> 3150 | E12: =SUM('Quarterly IS'!N12:Q12) -> 3550 | F12: =SUM('Quarterly IS'!R12:U12) -> 3975 | G12: =(F12/B12)^(1/4)-1 -> 0.14042655
A13: Selling, general & administrative | B13: =SUM('Quarterly IS'!B13:E13) -> 1895 | C13: =SUM('Quarterly IS'!F13:I13) -> 2165 | D13: =SUM('Quarterly IS'!J13:M13) -> 2445 | E13: =SUM('Quarterly IS'!N13:Q13) -> 2675 | F13: =SUM('Quarterly IS'!R13:U13) -> 2895 | G13: =(F13/B13)^(1/4)-1 -> 0.11175691
A14: Total operating expenses | B14: =B12+B13 -> 4245 | C14: =C12+C13 -> 4915 | D14: =D12+D13 -> 5595 | E14: =E12+E13 -> 6225 | F14: =F12+F13 -> 6870 | G14: =(F14/B14)^(1/4)-1 -> 0.12789783
A15: Operating income | B15: =B10-B14 -> 7755 | C15: =C10-C14 -> 15685 | D15: =D10-D14 -> 22855 | E15: =E10-E14 -> 25055 | F15: =F10-F14 -> 33380 | G15: =(F15/B15)^(1/4)-1 -> 0.44037685
A16: Operating margin (%) | B16: =B15/B8 -> 0.15698381 | C16: =C15/C8 -> 0.20802387 | D16: =D15/D8 -> 0.22167798 | E16: =E15/E8 -> 0.21345204 | F16: =F15/F8 -> 0.23204727 | G16: —
A17: Interest income | B17: =SUM('Quarterly IS'!B17:E17) -> 150 | C17: =SUM('Quarterly IS'!F17:I17) -> 230 | D17: =SUM('Quarterly IS'!J17:M17) -> 350 | E17: =SUM('Quarterly IS'!N17:Q17) -> 430 | F17: =SUM('Quarterly IS'!R17:U17) -> 510 | G17: =(F17/B17)^(1/4)-1 -> 0.35790607
A18: Interest expense | B18: =SUM('Quarterly IS'!B18:E18) -> 370 | C18: =SUM('Quarterly IS'!F18:I18) -> 410 | D18: =SUM('Quarterly IS'!J18:M18) -> 440 | E18: =SUM('Quarterly IS'!N18:Q18) -> 428 | F18: =SUM('Quarterly IS'!R18:U18) -> 412 | G18: =(F18/B18)^(1/4)-1 -> 0.027244614
A19: Other income/(expense), net | B19: =SUM('Quarterly IS'!B19:E19) -> 90 | C19: =SUM('Quarterly IS'!F19:I19) -> 10 | D19: =SUM('Quarterly IS'!J19:M19) -> 25 | E19: =SUM('Quarterly IS'!N19:Q19) -> 27 | F19: =SUM('Quarterly IS'!R19:U19) -> 35 | G19: =(F19/B19)^(1/4)-1 -> -0.21031046
A20: Pre-tax income | B20: =B15+B17-B18+B19 -> 7625 | C20: =C15+C17-C18+C19 -> 15515 | D20: =D15+D17-D18+D19 -> 22790 | E20: =E15+E17-E18+E19 -> 25084 | F20: =F15+F17-F18+F19 -> 33513 | G20: =(F20/B20)^(1/4)-1 -> 0.44791599
A21: Provision for income taxes | B21: =SUM('Quarterly IS'!B21:E21) -> 1525 | C21: =SUM('Quarterly IS'!F21:I21) -> 3103 | D21: =SUM('Quarterly IS'!J21:M21) -> 4558 | E21: =SUM('Quarterly IS'!N21:Q21) -> 5017 | F21: =SUM('Quarterly IS'!R21:U21) -> 6703 | G21: =(F21/B21)^(1/4)-1 -> 0.44793759
A22: Net income | B22: =B20-B21 -> 6100 | C22: =C20-C21 -> 12412 | D22: =D20-D21 -> 18232 | E22: =E20-E21 -> 20067 | F22: =F20-F21 -> 26810 | G22: =(F22/B22)^(1/4)-1 -> 0.44791059
A23: Net margin (%) | B23: =B22/B8 -> 0.12348178 | C23: =C22/C8 -> 0.16461538 | D23: =D22/D8 -> 0.17683802 | E23: =E22/E8 -> 0.17095757 | F23: =F22/F8 -> 0.1863747 | G23: —
A24: Diluted EPS (USD) | B24: =B22/Assumptions!$B$6 -> 1.7681159 | C24: =C22/Assumptions!$B$6 -> 3.5976812 | D24: =D22/Assumptions!$B$6 -> 5.2846377 | E24: =E22/Assumptions!$B$6 -> 5.8165217 | F24: =F22/Assumptions!$B$6 -> 7.7710145 | G24: =(F24/B24)^(1/4)-1 -> 0.44791059
A26: Total revenue YoY growth | C26: =C8/B8-1 -> 0.52631579 | D26: =D8/C8-1 -> 0.36737401 | E26: =E8/D8-1 -> 0.1385063 | F26: =F8/E8-1 -> 0.2255069
A27: Net income YoY growth | C27: =C22/B22-1 -> 1.0347541 | D27: =D22/C22-1 -> 0.46890106 | E27: =E22/D22-1 -> 0.10064721 | F27: =F22/E22-1 -> 0.33602432

Sheet Assumptions
A1: Tesla, Inc. — Synthetic Model Assumptions
A2: Synthetic example — NOT actual Tesla results. All figures are illustrative only.
A4: Parameter | B4: Value | C4: Notes
A5: Effective tax rate | B5: 0.2 | C5: Applied to pre-tax income each quarter (ROUND to whole USD millions)
A6: Diluted shares outstanding (M) | B6: 3450 | C6: Single synthetic average for all periods; EPS = Net income / shares
A7: Reporting currency / units | B7: USD millions | C7: All income statement rows are in USD millions except EPS (USD) and margins (%)
A8: Fiscal periods | B8: Calendar quarters, Q1 2021 – Q4 2025 | C8: 20 quarters; annual summary = sum of the four calendar quarters
A9: Revenue trajectory (synthetic) | B9: Automotive +~9%/qtr tapering to +~4%; Energy +~8–10%; Services +~6–7% | C9: Growth is decelerating as the base scales
A10: Cost of revenues (synthetic) | B10: ~80% of total revenue, declining to ~75.5% by 2025 | C10: ≈71–76% of total revenue by quarter (synthetic gross margin ≈24–29%)
A11: Operating expenses (synthetic) | B11: R&D and SG&A grow steadily; no restructuring charges | C11: R&D grows faster than SG&A
A12: Interest / other (synthetic) | B12: Interest income rises, interest expense declines; small other income/(expense) | C12: Net other items are minor
A13: Margin definitions | B13: Gross margin = Gross profit / Total revenues; Net margin = Net income / Total revenues | C13: Both displayed as percentages
A14: EPS definition | B14: Diluted EPS = Net income / diluted shares | C14: Constant synthetic share count of 3,450M
